hiddeneye_reborn/__init__.py
hiddeneye_reborn/hiddeneye.py
hiddeneye_reborn/config/__init__.py
hiddeneye_reborn/core/__init__.py
hiddeneye_reborn/core/config.py
hiddeneye_reborn/core/text_interface/__init__.py
hiddeneye_reborn/core/text_interface/main.py
hiddeneye_reborn/logs/__init__.py
hiddeneye_reborn/logs/default_logging.py
hiddeneye_reborn/network/__init__.py
hiddeneye_reborn/network/installation.py
hiddeneye_reborn/network/verification.py
hiddeneye_reborn/templating/__init__.py
hiddeneye_reborn-0.0a1.dev36.data/data/LICENSE
hiddeneye_reborn-0.0a1.dev36.dist-info/LICENSE
hiddeneye_reborn-0.0a1.dev36.dist-info/METADATA
hiddeneye_reborn-0.0a1.dev36.dist-info/WHEEL
hiddeneye_reborn-0.0a1.dev36.dist-info/entry_points.txt
hiddeneye_reborn-0.0a1.dev36.dist-info/top_level.txt
hiddeneye_reborn-0.0a1.dev36.dist-info/RECORD
