Metadata-Version: 2.1
Name: hiddeneye-reborn
Version: 0.0a1.dev36
Summary: Appropriate Phishing Tool
Home-page: https://github.com/Open-Security-Group-OSG/HiddenEyeReborn
Author: Open Security Group
Classifier: Development Status :: 1 - Planning
Classifier: Environment :: Console
Classifier: Environment :: Web Environment
Classifier: Intended Audience :: Education
Classifier: Intended Audience :: Information Technology
Classifier: Intended Audience :: Other Audience
Classifier: License :: OSI Approved :: The Unlicense (Unlicense)
Classifier: Natural Language :: English
Classifier: Operating System :: OS Independent
Classifier: Topic :: Education :: Testing
Classifier: Topic :: Internet
Classifier: Topic :: Security
Classifier: Topic :: Utilities
Classifier: Programming Language :: Python :: 3.6
Classifier: Programming Language :: Python :: 3.7
Classifier: Programming Language :: Python :: 3.8
Classifier: Programming Language :: Python :: 3.9
Classifier: Programming Language :: Python :: 3.10
Classifier: Programming Language :: Python :: 3.11
Requires-Python: >=3.6.*
License-File: LICENSE
Requires-Dist: pywebcopy
Requires-Dist: pyyaml
Requires-Dist: rich
